{"total":13,"pageSize":10,"pageCount":2,"current":1,"data":[{"title":"分支语句优化--状态模式","date":"2019-01-24T16:00:00.000Z","slug":"分支语句优化-状态模式"},{"title":"分支语句优化--策略模式","date":"2019-01-24T16:00:00.000Z","slug":"分支语句优化-策略模式"},{"title":"CSS 3D变换手册","date":"2018-11-29T16:00:00.000Z","slug":"CSS_3D变换手册"},{"title":"从Web到未来","date":"2018-03-29T11:44:54.000Z","slug":"从Web到未来"},{"title":"京东app中webview环境代理配置","date":"2018-01-25T16:00:00.000Z","slug":"京东app中webview环境代理配置"},{"title":"商城“智能”导航栏实践","date":"2017-12-15T16:00:00.000Z","slug":"商城“智能”导航栏实践"},{"title":"node实现的网站爬虫","date":"2017-09-21T16:00:00.000Z","slug":"node实现的网站爬虫"},{"title":"Express+MongoDB搭建多人博客","date":"2017-09-12T16:00:00.000Z","slug":"Express-MongoDB搭建多人博客"},{"title":"关于树形插件展示中数据结构转换的算法","date":"2017-06-02T16:00:00.000Z","slug":"关于树形插件展示中数据结构转换的算法"},{"title":"由setTimeout深入JavaScript执行环境的异步机制","date":"2017-05-22T16:00:00.000Z","slug":"由setTimeout深入JavaScript执行环境的异步机制"}],"name":"技术博客"}